rouge_torch/__init__.py
rouge_torch/core.py
rouge_torch/utils.py
rouge_torch-0.1.0.dist-info/licenses/LICENSE
rouge_torch-0.1.0.dist-info/METADATA
rouge_torch-0.1.0.dist-info/WHEEL
rouge_torch-0.1.0.dist-info/top_level.txt
rouge_torch-0.1.0.dist-info/RECORD
