Metadata-Version: 2.4
Name: rouge-torch
Version: 0.1.0
Summary: Fast differentiable ROUGE scores for PyTorch neural network training
Home-page: https://github.com/username/rouge-torch
Author: Rouge-Torch Contributors
Author-email: Rouge-Torch Contributors <contact@rouge-torch.dev>
Maintainer-email: Rouge-Torch Contributors <contact@rouge-torch.dev>
License: MIT
Project-URL: Homepage, https://github.com/username/rouge-torch
Project-URL: Documentation, https://rouge-torch.readthedocs.io/
Project-URL: Repository, https://github.com/username/rouge-torch.git
Project-URL: Bug Tracker, https://github.com/username/rouge-torch/issues
Project-URL: Changelog, https://github.com/username/rouge-torch/blob/main/CHANGELOG.md
Keywords: rouge,pytorch,nlp,natural language processing,text generation,evaluation metrics,differentiable,neural networks,machine learning,summarization,translation
Classifier: Development Status :: 4 - Beta
Classifier: Intended Audience :: Developers
Classifier: Intended Audience :: Science/Research
Classifier: License :: OSI Approved :: MIT License
Classifier: Operating System :: OS Independent
Classifier: Programming Language :: Python :: 3
Classifier: Programming Language :: Python :: 3.8
Classifier: Programming Language :: Python :: 3.9
Classifier: Programming Language :: Python :: 3.10
Classifier: Programming Language :: Python :: 3.11
Classifier: Programming Language :: Python :: 3.12
Classifier: Topic :: Scientific/Engineering :: Artificial Intelligence
Classifier: Topic :: Software Development :: Libraries :: Python Modules
Classifier: Topic :: Text Processing :: Linguistic
Requires-Python: >=3.8
License-File: LICENSE
Requires-Dist: torch>=1.9.0
Provides-Extra: dev
Requires-Dist: pytest>=6.0; extra == "dev"
Requires-Dist: pytest-cov; extra == "dev"
Requires-Dist: black; extra == "dev"
Requires-Dist: isort; extra == "dev"
Requires-Dist: flake8; extra == "dev"
Requires-Dist: mypy; extra == "dev"
Provides-Extra: test
Requires-Dist: pytest>=6.0; extra == "test"
Requires-Dist: pytest-cov; extra == "test"
Dynamic: author
Dynamic: home-page
Dynamic: license-file
Dynamic: requires-python
